avoma/__init__.py
avoma/api/__init__.py
avoma/api/calls.py
avoma/api/meetings.py
avoma/api/notes.py
avoma/api/recordings.py
avoma/api/sentiments.py
avoma/api/smart_categories.py
avoma/api/templates.py
avoma/api/transcriptions.py
avoma/api/users.py
avoma/client.py
avoma/logging.py
avoma/models/__init__.py
avoma/models/base.py
avoma/models/calls.py
avoma/models/meetings.py
avoma/models/notes.py
avoma/models/recordings.py
avoma/models/sentiments.py
avoma/models/smart_categories.py
avoma/models/templates.py
avoma/models/transcriptions.py
avoma/models/users.py
avoma_client-0.1.3.dist-info/LICENSE
avoma_client-0.1.3.dist-info/WHEEL
avoma_client-0.1.3.dist-info/METADATA
avoma_client-0.1.3.dist-info/RECORD
