Metadata-Version: 2.1
Name: avoma-client
Version: 0.1.3
Summary: An unofficial Python client for the Avoma API
Home-page: https://github.com/oztamir/avoma-client
License: MIT
Keywords: avoma,api,client
Author: Oz Tamir
Author-email: oz@atamir.fun
Requires-Python: >=3.11,<4.0
Classifier: License :: OSI Approved :: MIT License
Classifier: Programming Language :: Python :: 3
Classifier: Programming Language :: Python :: 3.11
Requires-Dist: aiohttp (>=3.9.3,<4.0.0)
Requires-Dist: email-validator (>=2.1.0,<3.0.0)
Requires-Dist: pydantic (>=2.6.1,<3.0.0)
Requires-Dist: urllib3 (>=2.0.0,<3.0.0)
Requires-Dist: yarl (>=1.9.4,<2.0.0)
Project-URL: Repository, https://github.com/oztamir/avoma-client
